foc/__init__.py
foc-0.6.4.dist-info/METADATA
foc-0.6.4.dist-info/WHEEL
foc-0.6.4.dist-info/top_level.txt
foc-0.6.4.dist-info/RECORD
