Metadata-Version: 2.4
Name: foc
Version: 0.6.4
Summary: A collection of python functions for somebody's sanity
Author-email: Taeho Francis Lim <thyeem@gmail.com>
Project-URL: Homepage, https://github.com/thyeem/foc
Keywords: functools,function-composition,functional-python,function-collection
Classifier: Topic :: Software Development :: Libraries :: Python Modules
Classifier: License :: OSI Approved :: MIT License
Classifier: Programming Language :: Python :: 3
Requires-Python: >=3.6
